sqlcrudbase/__init__.py
sqlcrudbase/base_controller.py
sqlcrudbase/base_repository.py
sqlcrudbase/base_service.py
sqlcrudbase-0.1.2.dist-info/LICENSE
sqlcrudbase-0.1.2.dist-info/METADATA
sqlcrudbase-0.1.2.dist-info/WHEEL
sqlcrudbase-0.1.2.dist-info/top_level.txt
sqlcrudbase-0.1.2.dist-info/RECORD
