Metadata-Version: 2.1
Name: sqlcrudbase
Version: 0.1.2
Summary: Python library to simplify the creation of CRUD operations in FastAPI applications.
Home-page: https://github.com/N3VERS4YDIE/sqlcrudbase-py-lib
Author: Santiago Palacio Vásquez
Author-email: keycode.santiago@gmail.com
License: MIT
Keywords: sql crud base peewee fastapi pydantic
License-File: LICENSE
Requires-Dist: fastapi
Requires-Dist: pydantic
Requires-Dist: peewee
